ho/__init__.py
ho/base.py
ho/util.py
ho-0.0.9.dist-info/LICENSE
ho-0.0.9.dist-info/METADATA
ho-0.0.9.dist-info/WHEEL
ho-0.0.9.dist-info/top_level.txt
ho-0.0.9.dist-info/RECORD
