Metadata-Version: 2.1
Name: ho
Version: 0.0.9
Summary: Http Objects - Tools to make python interfaces to http services
Home-page: https://github.com/i2mint/ho
License: mit
Platform: any
License-File: LICENSE
Requires-Dist: ju
Requires-Dist: requests
